pretix_pix_manual/__init__.py
pretix_pix_manual/apps.py
pretix_pix_manual/payment.py
pretix_pix_manual/pix.py
pretix_pix_manual/signals.py
pretix_pix_manual/locale/pt_BR/LC_MESSAGES/django.mo
pretix_pix_manual/locale/pt_BR/LC_MESSAGES/django.po
pretix_pix_manual/static/pretix_pix_manual/.gitkeep
pretix_pix_manual/templates/pretix_pix_manual/checkout_confirm.html
pretix_pix_manual/templates/pretix_pix_manual/payment_pending.html
pretix_pix_manual-0.2.0.dist-info/licenses/LICENSE
pretix_pix_manual-0.2.0.dist-info/METADATA
pretix_pix_manual-0.2.0.dist-info/WHEEL
pretix_pix_manual-0.2.0.dist-info/entry_points.txt
pretix_pix_manual-0.2.0.dist-info/top_level.txt
pretix_pix_manual-0.2.0.dist-info/RECORD
