Metadata-Version: 2.4
Name: pretix-pix-manual
Version: 0.2.0
Summary: Plugin for Brazilian Pix payment method with manual processing.
Author-email: Renne Rocha <renne@lhc.net.br>
Maintainer-email: Renne Rocha <renne@lhc.net.br>
License-Expression: AGPL-3.0-or-later
Project-URL: homepage, https://github.com/lhc/pretix-pix-manual
Project-URL: repository, https://github.com/lhc/pretix-pix-manual
Keywords: pretix
Classifier: Development Status :: 4 - Beta
Classifier: Programming Language :: Python
Classifier: Programming Language :: Python :: 3
License-File: LICENSE
Requires-Dist: qrcode
Dynamic: license-file
